antares_dotenv/__init__.py
antares_dotenv/core.py
antares_dotenv-1.1.0.dist-info/METADATA
antares_dotenv-1.1.0.dist-info/WHEEL
antares_dotenv-1.1.0.dist-info/licenses/LICENSE
antares_dotenv-1.1.0.dist-info/RECORD
