Metadata-Version: 2.4
Name: antares-dotenv
Version: 1.1.0
Summary: A minimal utility to load environment variables with automatic type casting.
License: MIT
License-File: LICENSE
Author: Antares Mugisho
Author-email: antaresmugisho@gmail.com
Requires-Python: >=3.11,<4.0
Classifier: License :: OSI Approved :: MIT License
Classifier: Programming Language :: Python :: 3
Classifier: Programming Language :: Python :: 3.11
Classifier: Programming Language :: Python :: 3.12
Classifier: Programming Language :: Python :: 3.13
Classifier: Programming Language :: Python :: 3.14
Requires-Dist: python-dotenv (>=1.1.0,<2.0.0)
